{
  "name": "org.wso2.apimgt.api.key.association.info.stream",
  "version": "1.0.0",
  "nickName": "",
  "description": "",
  "payloadData": [
    {
      "name": "eventId",
      "type": "STRING"
    },
    {
      "name": "keyDisplayName",
      "type": "STRING"
    },
    {
      "name": "keyType",
      "type": "STRING"
    },
    {
      "name": "apiKeyHash",
      "type": "STRING"
    },
    {
      "name": "apiUUId",
      "type": "STRING"
    },
    {
      "name": "applicationUUId",
      "type": "STRING"
    },
    {
      "name": "applicationId",
      "type": "INT"
    },
    {
      "name": "associationType",
      "type": "STRING"
    },
    {
      "name": "tenantId",
      "type": "INT"
    }
  ]
}